cms_bluebutton/__init__.py
cms_bluebutton/auth.py
cms_bluebutton/cms_bluebutton.py
cms_bluebutton/constants.py
cms_bluebutton/fhir_request.py
cms_bluebutton/version.py
cms_bluebutton_sdk-1.0.4.dist-info/licenses/LICENSE
cms_bluebutton_sdk-1.0.4.dist-info/METADATA
cms_bluebutton_sdk-1.0.4.dist-info/WHEEL
cms_bluebutton_sdk-1.0.4.dist-info/top_level.txt
cms_bluebutton_sdk-1.0.4.dist-info/RECORD
