Metadata-Version: 2.4
Name: cms-bluebutton-sdk
Version: 1.0.4
Summary: An SDK used for interacting with the CMS Blue Button 2.0 API
Author-email: "CMS Blue Button 2.0 Team" <BlueButtonAPI@cms.hhs.gov>
License-Expression: CC0-1.0
Classifier: Programming Language :: Python :: 3
Classifier: Operating System :: OS Independent
Classifier: Development Status :: 5 - Production/Stable
Classifier: Intended Audience :: Developers
Classifier: Intended Audience :: Healthcare Industry
Classifier: Topic :: Software Development
Classifier: Topic :: Software Development :: Libraries :: Python Modules
Requires-Python: >=3.9
License-File: LICENSE
Requires-Dist: requests>=2.32.3
Requires-Dist: requests-toolbelt>=0.9.1
Requires-Dist: pyyaml>=6.0.2
Requires-Dist: idna>=3.7
Requires-Dist: urllib3>=1.26.8
Requires-Dist: certifi==2025.1.31
Provides-Extra: dev
Requires-Dist: pylint>=2.14.0; extra == "dev"
Requires-Dist: toml>=0.10.2; extra == "dev"
Requires-Dist: pytest>=8.3.5; extra == "dev"
Requires-Dist: packaging>=24.0; extra == "dev"
Requires-Dist: flake8>=4.0.1; extra == "dev"
Requires-Dist: coverage>=6.3.2; extra == "dev"
Requires-Dist: requests-mock>=1.12.1; extra == "dev"
Requires-Dist: pyyaml>=6.0.2; extra == "dev"
Dynamic: license-file
